odoo10_addon_connector_lengow_fnac-10.0.1.0.0.99.dev3-py2.7-nspkg.pth
odoo/addons/connector_lengow_fnac/README.rst
odoo/addons/connector_lengow_fnac/__init__.py
odoo/addons/connector_lengow_fnac/__manifest__.py
odoo/addons/connector_lengow_fnac/data/lengow_data.xml
odoo/addons/connector_lengow_fnac/i18n/connector_lengow_fnac.pot
odoo/addons/connector_lengow_fnac/models/__init__.py
odoo/addons/connector_lengow_fnac/models/configurator.py
odoo/addons/connector_lengow_fnac/static/description/icon.png
odoo/addons/connector_lengow_fnac/tests/__init__.py
odoo/addons/connector_lengow_fnac/tests/test_lengow_stock.py
odoo10_addon_connector_lengow_fnac-10.0.1.0.0.99.dev3.dist-info/METADATA
odoo10_addon_connector_lengow_fnac-10.0.1.0.0.99.dev3.dist-info/RECORD
odoo10_addon_connector_lengow_fnac-10.0.1.0.0.99.dev3.dist-info/WHEEL
odoo10_addon_connector_lengow_fnac-10.0.1.0.0.99.dev3.dist-info/namespace_packages.txt
odoo10_addon_connector_lengow_fnac-10.0.1.0.0.99.dev3.dist-info/top_level.txt
